cdsaxs/__about__.py
cdsaxs/__init__.py
cdsaxs/fitter.py
cdsaxs/residual.py
cdsaxs/simulations/__init__.py
cdsaxs/simulations/base.py
cdsaxs/simulations/stacked_trapezoid.py
cdsaxs/simulations/strong_castle.py
cdsaxs-0.0.2.dist-info/METADATA
cdsaxs-0.0.2.dist-info/WHEEL
cdsaxs-0.0.2.dist-info/licenses/LICENSE.txt
cdsaxs-0.0.2.dist-info/RECORD
