Metadata-Version: 2.3
Name: cdsaxs
Version: 0.0.2
Summary: package streamlines CD-SAXS data analysis by combining model generation, optimization, and uncertainty estimation for nanostructure characterization
Project-URL: Documentation, https://github.com/CEA-MetroCarac/cdsaxs
Project-URL: Issues, https://github.com/CEA-MetroCarac/cdsaxs/issues
Project-URL: Source, https://github.com/CEA-MetroCarac/cdsaxs
Author-email: Nischal Dhungana <nischal.dhungana@cea.fr>
License-Expression: MIT
License-File: LICENSE.txt
Classifier: Development Status :: 4 - Beta
Classifier: Programming Language :: Python
Classifier: Programming Language :: Python :: 3.8
Classifier: Programming Language :: Python :: 3.9
Classifier: Programming Language :: Python :: 3.10
Classifier: Programming Language :: Python :: 3.11
Classifier: Programming Language :: Python :: 3.12
Classifier: Programming Language :: Python :: Implementation :: CPython
Classifier: Programming Language :: Python :: Implementation :: PyPy
Requires-Python: >=3.8
Requires-Dist: corner
Requires-Dist: deap
Requires-Dist: emcee
Requires-Dist: numpy
Requires-Dist: pandas
Requires-Dist: scipy
Provides-Extra: gpu
Requires-Dist: cupy>=9.0.0; extra == 'gpu'
